{
  "project_info": {
    "project_number": "514206301078",
    "firebase_url": "https://yobro-215722.firebaseio.com",
    "project_id": "yobro-215722",
    "storage_bucket": "yobro-215722.appspot.com"
  },
  "client": [
    {
      "client_info": {
        "mobilesdk_app_id": "1:514206301078:android:bf3559637c3cd502",
        "android_client_info": {
          "package_name": "com.yobro"
        }
      },
      "oauth_client": [
        {
          "client_id": "514206301078-m54avcf2459st75v9ki96b9gusbscf2r.apps.googleusercontent.com",
          "client_type": 1,
          "android_info": {
            "package_name": "com.yobro",
            "certificate_hash": "077ad396b83fcafae690ee5a3045453650eebc8f"
          }
        },
        {
          "client_id": "514206301078-9go2nt63bmu78b6utnishc89qtlrd0rd.apps.googleusercontent.com",
          "client_type": 1,
          "android_info": {
            "package_name": "com.yobro",
            "certificate_hash": "6933979b72b866c70d024540a869bd0738c82077"
          }
        },
        {
          "client_id": "514206301078-807cgkj003ejb0mjr9ed32k02sj1407a.apps.googleusercontent.com",
          "client_type": 1,
          "android_info": {
            "package_name": "com.yobro",
            "certificate_hash": "3fb73e68deca807b9cc31a93f50f8883bb06d857"
          }
        },
        {
          "client_id": "514206301078-i4k12nnittaqjpgftr7h7h8f14chrrag.apps.googleusercontent.com",
          "client_type": 1,
          "android_info": {
            "package_name": "com.yobro",
            "certificate_hash": "9c43899a10bf9aa9c4227255783b9f492a9ae7df"
          }
        },
        {
          "client_id": "514206301078-c07tlf764nqnm9iod084lq9e6riqvi01.apps.googleusercontent.com",
          "client_type": 3
        }
      ],
      "api_key": [
        {
          "current_key": "AIzaSyAafI-DHSD9UgHsZJrJNhQhOux_75ji5Po"
        },
        {
          "current_key": "AIzaSyBCLWKaKORTUAh9WmldhFKt7OkYxv_ZHj4"
        },
        {
          "current_key": "AIzaSyCvUdn-idqO3Wfxv0uq6ilUhFKvRFgJ3Ys"
        },
        {
          "current_key": "AIzaSyAGINdIAltqIiegaeWGUn8d9T9AhWKYVcI"
        },
        {
          "current_key": "AIzaSyDonCIqxFkz9Zh3yCrJR2ZI14rQF6rZjac"
        }
      ],
      "services": {
        "analytics_service": {
          "status": 1
        },
        "appinvite_service": {
          "status": 2,
          "other_platform_oauth_client": [
            {
              "client_id": "514206301078-c07tlf764nqnm9iod084lq9e6riqvi01.apps.googleusercontent.com",
              "client_type": 3
            }
          ]
        },
        "ads_service": {
          "status": 2
        }
      }
    }
  ],
  "configuration_version": "1"
}